pyuse/__init__.py
pyuse/dingtalk.py
pyuse/generator.py
pyuse/path.py
pyuse/time.py
pyuse_core-0.0.3.dist-info/METADATA
pyuse_core-0.0.3.dist-info/WHEEL
pyuse_core-0.0.3.dist-info/top_level.txt
pyuse_core-0.0.3.dist-info/RECORD
