Metadata-Version: 2.1
Name: pyuse-core
Version: 0.0.3
Summary: A pkg of wheels. Hope it helps you to write less code.
Home-page: https://github.com/yongchin0821/pyuse
Author: Yongchin
Author-email: yongchin39@qq.com
Project-URL: Bug Tracker, https://github.com/yongchin0821/pyuse/issues
Classifier: Programming Language :: Python :: 3
Classifier: License :: OSI Approved :: MIT License
Classifier: Operating System :: OS Independent
Requires-Python: >=3.6
